script_utilities/__init__.py
script_utilities/constants.py
script_utilities/date.py
script_utilities/file.py
script_utilities/functions.py
script_utilities/mkw.py
script_utilities-0.6.1.dist-info/METADATA
script_utilities-0.6.1.dist-info/WHEEL
script_utilities-0.6.1.dist-info/licenses/LICENSE
script_utilities-0.6.1.dist-info/RECORD
