Metadata-Version: 2.4
Name: script-utilities
Version: 0.6.1
Summary: A Python package containing useful functions and classes for scripting MKW-related projects.
Project-URL: repository, https://github.com/Krummers/Script-Utilities
Project-URL: issues, https://github.com/Krummers/Script-Utilities/issues
Project-URL: releasenotes, https://github.com/Krummers/Script-Utilities/releases
Author-email: Krummers <krummers10@gmail.com>
License:                     GNU GENERAL PUBLIC LICENSE
License-File: LICENSE
Classifier: License :: OSI Approved :: GNU General Public License v3 (GPLv3)
Classifier: Programming Language :: Python :: 3.10
Classifier: Programming Language :: Python :: 3.11
Classifier: Programming Language :: Python :: 3.12
Requires-Python: >=3.10
Requires-Dist: httpx
Requires-Dist: httpx[http2]
Requires-Dist: tdqm
